taggo/__init__.py
taggo/__main__.py
taggo/exceptions.py
taggo/filters.py
taggo/utils.py
taggo/metadata/10_stat.py
taggo/metadata/15_filetype.py
taggo/metadata/20_exif.py
taggo/metadata/40_md5.py
taggo/metadata/__init__.py
taggo-0.18.0.dist-info/AUTHORS.rst
taggo-0.18.0.dist-info/LICENSE
taggo-0.18.0.dist-info/METADATA
taggo-0.18.0.dist-info/WHEEL
taggo-0.18.0.dist-info/entry_points.txt
taggo-0.18.0.dist-info/top_level.txt
taggo-0.18.0.dist-info/RECORD
