Metadata-Version: 2.1
Name: taggo
Version: 0.18.0
Summary: Tag organizer that creates symlinks from filename-tags
Home-page: https://github.com/xeor/taggo
Author: Lars Solberg
Author-email: lars.solberg@gmail.com
License: MIT license
Keywords: taggo
Platform: UNKNOWN
Classifier: Development Status :: 4 - Beta
Classifier: Intended Audience :: Developers
Classifier: Intended Audience :: Information Technology
Classifier: Intended Audience :: System Administrators
Classifier: Topic :: System :: Filesystems
Classifier: License :: OSI Approved :: MIT License
Classifier: Natural Language :: English
Classifier: Programming Language :: Python :: 3.6
Requires-Dist: jmespath
Requires-Dist: python-box
Provides-Extra: allmeta
Requires-Dist: piexif ; extra == 'allmeta'
Requires-Dist: filetype ; extra == 'allmeta'
Provides-Extra: frontmatter
Requires-Dist: python-frontmatter ; extra == 'frontmatter'
Provides-Extra: winlnk
Requires-Dist: pywin32 ; extra == 'winlnk'
